localstorage_flask/__init__.py
localstorage_flask-2.0.1.dist-info/METADATA
localstorage_flask-2.0.1.dist-info/WHEEL
localstorage_flask-2.0.1.dist-info/top_level.txt
localstorage_flask-2.0.1.dist-info/RECORD
