Metadata-Version: 2.1
Name: localstorage_flask
Version: 2.0.1
Summary: A Flask extension for local storage
Home-page: https://github.com/bobbyshop-vui/localstorage_flask.git
Author: Bobby
Author-email: info@bobby-shop.com
Classifier: Programming Language :: Python :: 3
Classifier: License :: OSI Approved :: MIT License
Classifier: Operating System :: OS Independent
Requires-Python: >=3.0
Requires-Dist: Flask
